README.md
setup.cfg
setup.py
MandarProductionalizingProject_1.egg-info/PKG-INFO
MandarProductionalizingProject_1.egg-info/SOURCES.txt
MandarProductionalizingProject_1.egg-info/dependency_links.txt
MandarProductionalizingProject_1.egg-info/requires.txt
MandarProductionalizingProject_1.egg-info/top_level.txt
mypackage/__init__.py
mypackage/mymodule.py