Metadata-Version: 1.1
Name: MandarProductionalizingProject-1
Version: 0.3
Summary: This should be a short description of our project
Home-page: https://github.com/rmandar16
Author: Mandar Raibagi
Author-email: rmandar16@gmail.com
License: UNKNOWN
Keywords: test,class
Platform: UNKNOWN
Classifier: Programming Language :: Python :: 3
Classifier: Programming Language :: Python :: 3.7
